SuitecrmPythonClient
