Metadata-Version: 2.1
Name: SuitecrmPythonClient
Version: 0.0.8
Summary: Python package which provides Suitecrm Client
Home-page: https://github.com/rmetcalf9/SuitecrmPythonClient
Author: Robert Metcalf
Author-email: rmetcalf9@googlemail.com
License: MIT
Platform: UNKNOWN
